[
    {
        "componentChunkName": "component---src-pages-index-js",
        "jsonName": "index",
        "path": "/"
    },
    {
        "componentChunkName": "component---src-pages-background-color-js",
        "jsonName": "background-color-a9b",
        "path": "/background-color/"
    },
    {
        "componentChunkName": "component---src-pages-blur-up-js",
        "jsonName": "blur-up-566",
        "path": "/blur-up/"
    },
    {
        "componentChunkName": "component---cache-dev-404-page-js",
        "jsonName": "dev-404-page-5f9",
        "path": "/dev-404-page/"
    },
    {
        "componentChunkName": "component---src-pages-prefer-webp-js",
        "jsonName": "prefer-webp-233",
        "path": "/prefer-webp/"
    },
    {
        "componentChunkName": "component---src-pages-traced-svg-js",
        "jsonName": "traced-svg-35c",
        "path": "/traced-svg/"
    }
]